taskbridge/__init__.py
taskbridge/cli/__init__.py
taskbridge/cli/tbcli.py
taskbridge/gui/TaskBridge.py
taskbridge/gui/__init__.py
taskbridge/gui/about.ui
taskbridge/gui/assets/AppIcons/Assets.xcassets/AppIcon.appiconset/100.png
taskbridge/gui/assets/AppIcons/Assets.xcassets/AppIcon.appiconset/102.png
taskbridge/gui/assets/AppIcons/Assets.xcassets/AppIcon.appiconset/1024.png
taskbridge/gui/assets/AppIcons/Assets.xcassets/AppIcon.appiconset/114.png
taskbridge/gui/assets/AppIcons/Assets.xcassets/AppIcon.appiconset/120.png
taskbridge/gui/assets/AppIcons/Assets.xcassets/AppIcon.appiconset/128.png
taskbridge/gui/assets/AppIcons/Assets.xcassets/AppIcon.appiconset/144.png
taskbridge/gui/assets/AppIcons/Assets.xcassets/AppIcon.appiconset/152.png
taskbridge/gui/assets/AppIcons/Assets.xcassets/AppIcon.appiconset/16.png
taskbridge/gui/assets/AppIcons/Assets.xcassets/AppIcon.appiconset/167.png
taskbridge/gui/assets/AppIcons/Assets.xcassets/AppIcon.appiconset/172.png
taskbridge/gui/assets/AppIcons/Assets.xcassets/AppIcon.appiconset/180.png
taskbridge/gui/assets/AppIcons/Assets.xcassets/AppIcon.appiconset/196.png
taskbridge/gui/assets/AppIcons/Assets.xcassets/AppIcon.appiconset/20.png
taskbridge/gui/assets/AppIcons/Assets.xcassets/AppIcon.appiconset/216.png
taskbridge/gui/assets/AppIcons/Assets.xcassets/AppIcon.appiconset/256.png
taskbridge/gui/assets/AppIcons/Assets.xcassets/AppIcon.appiconset/29.png
taskbridge/gui/assets/AppIcons/Assets.xcassets/AppIcon.appiconset/32.png
taskbridge/gui/assets/AppIcons/Assets.xcassets/AppIcon.appiconset/40.png
taskbridge/gui/assets/AppIcons/Assets.xcassets/AppIcon.appiconset/48.png
taskbridge/gui/assets/AppIcons/Assets.xcassets/AppIcon.appiconset/50.png
taskbridge/gui/assets/AppIcons/Assets.xcassets/AppIcon.appiconset/512.png
taskbridge/gui/assets/AppIcons/Assets.xcassets/AppIcon.appiconset/55.png
taskbridge/gui/assets/AppIcons/Assets.xcassets/AppIcon.appiconset/57.png
taskbridge/gui/assets/AppIcons/Assets.xcassets/AppIcon.appiconset/58.png
taskbridge-0.1.1.dist-info/LICENSE
taskbridge-0.1.1.dist-info/METADATA
taskbridge-0.1.1.dist-info/WHEEL
taskbridge-0.1.1.dist-info/entry_points.txt
taskbridge-0.1.1.dist-info/RECORD
